imsane/__init__.py
imsane/linop.py
imsane/optim.py
imsane/sampling.py
imsane-0.0.2.dist-info/METADATA
imsane-0.0.2.dist-info/WHEEL
imsane-0.0.2.dist-info/licenses/LICENSE
imsane-0.0.2.dist-info/RECORD
