Metadata-Version: 2.4
Name: imsane
Version: 0.0.2
Summary: A collection of sane implementations of linear operators and various algorithms in sampling and optimization implemented in python/pytorch.
Project-URL: Homepage, https://github.com/zacmar/sane
Project-URL: Issues, https://github.com/zacmar/sane/issues
Author-email: Martin Zach <me@martin-zach.com>
License-Expression: Apache-2.0
License-File: LICENSE
Keywords: imaging problems,inverse imaging,linear operators,markov chain monte carlo,optimization,sampling
Requires-Python: >=3.12
